MANIFEST.in
README.md
setup.py
./opentc/__init__.py
./opentc/util/__init__.py
./opentc/util/client.py
./opentc/util/setting.py
opentc_util.egg-info/PKG-INFO
opentc_util.egg-info/SOURCES.txt
opentc_util.egg-info/dependency_links.txt
opentc_util.egg-info/not-zip-safe
opentc_util.egg-info/requires.txt
opentc_util.egg-info/top_level.txt