Metadata-Version: 1.1
Name: opentc-util
Version: 0.1.0
Summary: The util package of OpenTC (A text classification engine using machine learning)
Home-page: https://github.com/cahya-wirawan/opentc-util
Author: Cahya Wirawan
Author-email: Cahya.Wirawan@gmail.com
License: MIT
Keywords: machine learning cnn svm bayesian
Platform: UNKNOWN
Classifier: Development Status :: 3 - Alpha
Classifier: License :: OSI Approved :: MIT License
Classifier: Programming Language :: Python :: 3.5
Classifier: Topic :: Scientific/Engineering :: Artificial Intelligence
Classifier: Topic :: Text Processing :: Filters
